LICENSE
README.md
setup.py
DNSBruter.egg-info/PKG-INFO
DNSBruter.egg-info/SOURCES.txt
DNSBruter.egg-info/dependency_links.txt
DNSBruter.egg-info/entry_points.txt
DNSBruter.egg-info/requires.txt
DNSBruter.egg-info/top_level.txt
dnsbruter/__init__.py
dnsbruter/dnsbruter.py
dnsbruter/modules/__init__.py
dnsbruter/modules/handler.py
dnsbruter/modules/banner/__init__.py
dnsbruter/modules/banner/banner.py
dnsbruter/modules/cli/__init__.py
dnsbruter/modules/cli/cli.py
dnsbruter/modules/core/__init__.py
dnsbruter/modules/core/core.py
dnsbruter/modules/extender/__init__.py
dnsbruter/modules/extender/extender.py
dnsbruter/modules/help/__init__.py
dnsbruter/modules/help/help.py
dnsbruter/modules/logger/__init__.py
dnsbruter/modules/logger/logger.py
dnsbruter/modules/save/__init__.py
dnsbruter/modules/save/save.py
dnsbruter/modules/utils/__init__.py
dnsbruter/modules/utils/utils.py
dnsbruter/modules/version/__init__.py
dnsbruter/modules/version/version.py
dnsbruter/modules/wildcards/__init__.py
dnsbruter/modules/wildcards/wildcards.py