Metadata-Version: 2.1
Name: DNSBruter
Version: 1.0.6
Summary: dnsbruter is a powerful tool for asynchronous DNS bruteforcing and fuzzing with wildcard detection
Home-page: https://github.com/RevoltSecurities/Dnsbruter
Author: D. Sanjai Kumar @RevoltSecurities
Author-email: bughunterz0047@gmail.com
License-File: LICENSE
